<?xml version="1.0" encoding="UTF-8"?>
<Index xmlns="http://www.tso.co.uk/assets/namespace/gazetteindex" editionCode="L" page="073" pageID="https://www.thegazette.co.uk/id/London/index/year/1940/volume/1/page/073" pagePDF="https://www.thegazette.co.uk/London/index/year/1940/volume/1/page/073" pageRDF="https://www.thegazette.co.uk/London/index/year/1940/volume/1/page/073?view=linked-data" type="index" volume="1" year="1940">
  <ItemGroup>
    <MainItem>
      <Key>Reynolds</Key>
      <Forenames>F. H.</Forenames>
      <PageNumber>383</PageNumber>
    </MainItem>
  </ItemGroup>
  <ItemGroup>
    <MainItem>
      <Key>Richmond</Key>
      <Forenames>G. N.</Forenames>
      <PageNumber>383</PageNumber>
    </MainItem>
  </ItemGroup>
  <ItemGroup>
    <MainItem>
      <Key>Ridge</Key>
      <Text>way, D. G</Text>
      <PageNumber>227</PageNumber>
    </MainItem>
  </ItemGroup>
  <ItemGroup>
    <MainItem>
      <Key>Ridout</Key>
      <Forenames>W. L</Forenames>
      <PageNumber>93</PageNumber>
    </MainItem>
  </ItemGroup>
  <ItemGroup>
    <MainItem>
      <Key>Roach</Key>
      <Forenames>R. A.</Forenames>
      <PageNumber>1712</PageNumber>
    </MainItem>
  </ItemGroup>
  <ItemGroup>
    <MainItem>
      <Key>Robertson</Key>
      <Forenames>H. F.</Forenames>
      <PageNumber>383</PageNumber>
    </MainItem>
  </ItemGroup>
  <ItemGroup>
    <MainItem>
      <Key>Robinson</Key>
      <Forenames>H. G. W</Forenames>
      <PageNumber>93</PageNumber>
    </MainItem>
  </ItemGroup>
  <ItemGroup>
    <MainItem>
      <Key>
        <KeyDitto>___ ___ ___ ].</KeyDitto>
      </Key>
      <Forenames>F</Forenames>
      <PageNumber>790</PageNumber>
    </MainItem>
  </ItemGroup>
  <ItemGroup>
    <MainItem>
      <Key>Rodrigues</Key>
      <Forenames>E. A.</Forenames>
      <PageNumber>790</PageNumber>
    </MainItem>
  </ItemGroup>
  <ItemGroup>
    <MainItem>
      <Key>Rogers</Key>
      <Forenames>C. F.</Forenames>
      <PageNumber>1105</PageNumber>
    </MainItem>
  </ItemGroup>
  <ItemGroup>
    <MainItem>
      <Key>Rowe</Key>
      <Forenames>J. J.</Forenames>
      <PageNumber>661</PageNumber>
    </MainItem>
  </ItemGroup>
  <ItemGroup>
    <MainItem>
      <Key>Rowley</Key>
      <Forenames>J. R. E.</Forenames>
      <PageNumber>1711</PageNumber>
    </MainItem>
  </ItemGroup>
  <ItemGroup>
    <MainItem>
      <Key>Rumbold</Key>
      <Forenames>W. A</Forenames>
      <PageNumber>790</PageNumber>
    </MainItem>
  </ItemGroup>
  <ItemGroup>
    <MainItem>
      <Key>Russell</Key>
      <Forenames>H. L. V</Forenames>
      <PageNumber>790</PageNumber>
    </MainItem>
  </ItemGroup>
  <ItemGroup>
    <MainItem>
      <Key>Rustomji</Key>
      <Forenames>Maneckji Bilimoria</Forenames>
      <PageNumber>1711</PageNumber>
    </MainItem>
  </ItemGroup>
  <ItemGroup>
    <MainItem>
      <Key>Ryan</Key>
      <Forenames>D. G.</Forenames>
      <Text>... Sanders, G. P</Text>
      <PageNumber>1543</PageNumber>
    </MainItem>
  </ItemGroup>
  <ItemGroup>
    <MainItem>
      <Key>
        <KeyDitto>___ ___ ___</KeyDitto>
      </Key>
      <Forenames>G. P. V</Forenames>
      <PageNumber>1711</PageNumber>
    </MainItem>
  </ItemGroup>
  <ItemGroup>
    <MainItem>
      <Key>Saunders</Key>
      <Forenames>P. T.</Forenames>
      <PageNumber>1246</PageNumber>
    </MainItem>
  </ItemGroup>
  <ItemGroup>
    <MainItem>
      <Key>Sawtell</Key>
      <Forenames>J</Forenames>
      <PageNumber>791</PageNumber>
    </MainItem>
  </ItemGroup>
  <ItemGroup>
    <MainItem>
      <Key>Sayres</Key>
      <Forenames>R. J.</Forenames>
      <PageNumber>383</PageNumber>
    </MainItem>
  </ItemGroup>
  <ItemGroup>
    <MainItem>
      <Key>Scott</Key>
      <Forenames>F. B</Forenames>
      <PageNumber>1712</PageNumber>
    </MainItem>
  </ItemGroup>
  <ItemGroup>
    <MainItem>
      <Key>
        <KeyDitto>___ ___</KeyDitto>
      </Key>
      <Forenames>R. B</Forenames>
      <PageNumber>790</PageNumber>
    </MainItem>
  </ItemGroup>
  <ItemGroup>
    <MainItem>
      <Key>Seaward</Key>
      <Forenames>W. G</Forenames>
      <PageNumber>227</PageNumber>
      <PageNumber>1105</PageNumber>
    </MainItem>
  </ItemGroup>
  <ItemGroup>
    <MainItem>
      <Key>Shakespear</Key>
      <Forenames>L. T. C.</Forenames>
      <PageNumber>227</PageNumber>
      <PageNumber>1105</PageNumber>
    </MainItem>
  </ItemGroup>
  <ItemGroup>
    <MainItem>
      <Key>Shaw</Key>
      <Forenames>N. F. B</Forenames>
      <PageNumber>790</PageNumber>
    </MainItem>
  </ItemGroup>
  <ItemGroup>
    <MainItem>
      <Key>Sheikh</Key>
      <Forenames>K. M</Forenames>
      <PageNumber>1711</PageNumber>
    </MainItem>
  </ItemGroup>
  <ItemGroup>
    <MainItem>
      <Key>Shenton</Key>
      <Forenames>K. A</Forenames>
      <PageNumber>1849</PageNumber>
    </MainItem>
  </ItemGroup>
  <ItemGroup>
    <MainItem>
      <Key>Shepherd</Key>
      <Forenames>G. H</Forenames>
      <PageNumber>531</PageNumber>
    </MainItem>
  </ItemGroup>
  <ItemGroup>
    <MainItem>
      <Key>Sherred</Key>
      <Forenames>B. E</Forenames>
      <PageNumber>928</PageNumber>
    </MainItem>
  </ItemGroup>
  <ItemGroup>
    <MainItem>
      <Key>Shipway</Key>
      <Forenames>W. G.</Forenames>
      <PageNumber>661</PageNumber>
    </MainItem>
  </ItemGroup>
  <ItemGroup>
    <MainItem>
      <Key>Shirley</Key>
      <Forenames>R. C.</Forenames>
      <Text>de la C</Text>
      <PageNumber>227</PageNumber>
    </MainItem>
  </ItemGroup>
  <ItemGroup>
    <MainItem>
      <Key>Shuker</Key>
      <Forenames>H.</Forenames>
      <PageNumber>1105</PageNumber>
    </MainItem>
  </ItemGroup>
  <ItemGroup>
    <MainItem>
      <Key>Simmons</Key>
      <Forenames>E. C.</Forenames>
      <PageNumber>383</PageNumber>
    </MainItem>
  </ItemGroup>
  <ItemGroup>
    <MainItem>
      <Key>Sisley</Key>
      <Forenames>F. W.</Forenames>
      <PageNumber>383</PageNumber>
    </MainItem>
  </ItemGroup>
  <ItemGroup>
    <MainItem>
      <Key>Skipwith</Key>
      <Forenames>J. P.</Forenames>
      <Text>dE</Text>
      <PageNumber>93</PageNumber>
      <PageNumber>661</PageNumber>
    </MainItem>
  </ItemGroup>
  <ItemGroup>
    <MainItem>
      <Key>Slade</Key>
      <Forenames>J. W</Forenames>
      <Text>C</Text>
      <PageNumber>383</PageNumber>
    </MainItem>
  </ItemGroup>
  <ItemGroup>
    <MainItem>
      <Key>Smitz</Key>
      <Forenames>W. B</Forenames>
      <PageNumber>383</PageNumber>
    </MainItem>
  </ItemGroup>
  <ItemGroup>
    <MainItem>
      <Key>Smythe</Key>
      <Forenames>A. C. G</Forenames>
      <PageNumber>790</PageNumber>
    </MainItem>
  </ItemGroup>
  <ItemGroup>
    <MainItem>
      <Key>Sobhakar</Key>
      <Forenames>Day</Forenames>
      <PageNumber>1712</PageNumber>
    </MainItem>
  </ItemGroup>
  <ItemGroup>
    <MainItem>
      <Key>Som-Dutt</Key>
      <Forenames>D</Forenames>
      <PageNumber>1711</PageNumber>
    </MainItem>
  </ItemGroup>
  <ItemGroup>
    <MainItem>
      <Key>Sorby</Key>
      <Forenames>R. A. C</Forenames>
      <PageNumber>790</PageNumber>
    </MainItem>
  </ItemGroup>
  <ItemGroup>
    <MainItem>
      <Key>Southam</Key>
      <Forenames>F. A</Forenames>
      <Text>,»</Text>
      <PageNumber>227</PageNumber>
    </MainItem>
  </ItemGroup>
  <ItemGroup>
    <MainItem>
      <Key>Southgate</Key>
      <Forenames>E. H. D</Forenames>
      <PageNumber>1849</PageNumber>
    </MainItem>
  </ItemGroup>
  <ItemGroup>
    <MainItem>
      <Key>Stephenson</Key>
      <Forenames>J. D.</Forenames>
      <PageNumber>227</PageNumber>
    </MainItem>
  </ItemGroup>
  <ItemGroup>
    <MainItem>
      <Key>Stewart</Key>
      <Forenames>A. F</Forenames>
      <PageNumber>1711</PageNumber>
    </MainItem>
  </ItemGroup>
  <ItemGroup>
    <MainItem>
      <Key>
        <KeyDitto>___</KeyDitto>
      </Key>
      <Forenames>H. I. E. R. C</Forenames>
      <PageNumber>706</PageNumber>
    </MainItem>
  </ItemGroup>
  <ItemGroup>
    <MainItem>
      <Key>Stoney</Key>
      <Forenames>P. S.</Forenames>
      <PageNumber>790</PageNumber>
    </MainItem>
  </ItemGroup>
  <ItemGroup>
    <MainItem>
      <Key>Sutherland</Key>
      <Forenames>C.</Forenames>
      <PageNumber>383</PageNumber>
    </MainItem>
  </ItemGroup>
  <ItemGroup>
    <MainItem>
      <Key>
        <KeyDitto>___ ___</KeyDitto>
      </Key>
      <Forenames>J. W. R.</Forenames>
      <PageNumber>383</PageNumber>
    </MainItem>
  </ItemGroup>
  <ItemGroup>
    <MainItem>
      <Key>
        <KeyDitto>___ ___ ___ ___</KeyDitto>
      </Key>
      <Forenames>R. L. M.</Forenames>
      <PageNumber>227</PageNumber>
      <PageNumber>1105</PageNumber>
    </MainItem>
  </ItemGroup>
  <ItemGroup>
    <MainItem>
      <Key>Tandy</Key>
      <Forenames>M. P. O</Forenames>
      <Text>'C</Text>
      <PageNumber>928</PageNumber>
      <PageNumber>1711</PageNumber>
    </MainItem>
  </ItemGroup>
  <ItemGroup>
    <MainItem>
      <Key>Taylor</Key>
      <Forenames>G. D.</Forenames>
      <PageNumber>1104</PageNumber>
    </MainItem>
  </ItemGroup>
  <ItemGroup>
    <MainItem>
      <Key>Thompson</Key>
      <Forenames>E. J.</Forenames>
      <PageNumber>1105</PageNumber>
    </MainItem>
  </ItemGroup>
  <ItemGroup>
    <MainItem>
      <Key>Thwaytes</Key>
      <Forenames>L. L.</Forenames>
      <PageNumber>1104</PageNumber>
    </MainItem>
  </ItemGroup>
  <ItemGroup>
    <MainItem>
      <Key>Toms</Key>
      <Forenames>H. G.</Forenames>
      <PageNumber>1246</PageNumber>
    </MainItem>
  </ItemGroup>
  <ItemGroup>
    <MainItem>
      <Key>Toogood</Key>
      <Forenames>C. G.</Forenames>
      <PageNumber>1105</PageNumber>
    </MainItem>
  </ItemGroup>
  <ItemGroup>
    <MainItem>
      <Key>Trenam</Key>
      <Forenames>D.</Forenames>
      <PageNumber>227</PageNumber>
      <PageNumber>1105</PageNumber>
    </MainItem>
  </ItemGroup>
  <ItemGroup>
    <MainItem>
      <Key>Trewby</Key>
      <Forenames>H. F.</Forenames>
      <PageNumber>790</PageNumber>
    </MainItem>
  </ItemGroup>
  <ItemGroup>
    <MainItem>
      <Key>Tugwell</Key>
      <Forenames>L. B. O.</Forenames>
      <PageNumber>227</PageNumber>
      <PageNumber>1105</PageNumber>
    </MainItem>
  </ItemGroup>
  <ItemGroup>
    <MainItem>
      <Key>Tyndale</Key>
      <Forenames>C. H. G</Forenames>
      <PageNumber>93</PageNumber>
    </MainItem>
  </ItemGroup>
  <ItemGroup>
    <MainItem>
      <Key>Upton</Key>
      <Forenames>H. E. P. M. S.</Forenames>
      <PageNumber>93</PageNumber>
    </MainItem>
  </ItemGroup>
  <ItemGroup>
    <MainItem>
      <Key>Vicary</Key>
      <Forenames>E. S.</Forenames>
      <PageNumber>227</PageNumber>
    </MainItem>
  </ItemGroup>
  <ItemGroup>
    <MainItem>
      <Key>Vincent</Key>
      <Forenames>S. A.</Forenames>
      <PageNumber>928</PageNumber>
    </MainItem>
  </ItemGroup>
  <ItemGroup>
    <MainItem>
      <Key>Voelcker</Key>
      <Forenames>D. C</Forenames>
      <PageNumber>790</PageNumber>
    </MainItem>
  </ItemGroup>
  <ItemGroup>
    <MainItem>
      <Key>Vorley</Key>
      <Forenames>J. S.</Forenames>
      <PageNumber>383</PageNumber>
    </MainItem>
  </ItemGroup>
  <ItemGroup>
    <MainItem>
      <Key>Waddilove</Key>
      <Forenames>M. C.</Forenames>
      <PageNumber>1711</PageNumber>
    </MainItem>
  </ItemGroup>
  <ItemGroup>
    <MainItem>
      <Key>Wadia</Key>
      <Forenames>L. M. H.</Forenames>
      <PageNumber>1711</PageNumber>
    </MainItem>
  </ItemGroup>
  <ItemGroup>
    <MainItem>
      <Key>Wakefield</Key>
      <Forenames>E. G.</Forenames>
      <PageNumber>1711</PageNumber>
    </MainItem>
  </ItemGroup>
  <ItemGroup>
    <MainItem>
      <Key>Walker</Key>
      <Forenames>B. W. G.</Forenames>
      <PageNumber>1105</PageNumber>
    </MainItem>
  </ItemGroup>
  <ItemGroup>
    <MainItem>
      <Key>
        <KeyDitto>___ ___</KeyDitto>
      </Key>
      <Forenames>E. R</Forenames>
      <PageNumber>1712</PageNumber>
    </MainItem>
  </ItemGroup>
  <ItemGroup>
    <MainItem>
      <Key>
        <KeyDitto>___ ___ ___</KeyDitto>
      </Key>
      <Forenames>R. C.</Forenames>
      <PageNumber>1712</PageNumber>
    </MainItem>
  </ItemGroup>
  <ItemGroup>
    <MainItem>
      <Key>Walsh</Key>
      <Forenames>E. G. W. T.</Forenames>
      <Text>... ..; '</Text>
      <PageNumber>93</PageNumber>
    </MainItem>
  </ItemGroup>
  <ItemGroup>
    <MainItem>
      <Key>Walter</Key>
      <Forenames>N. I.</Forenames>
      <Text>McN</Text>
      <PageNumber>227</PageNumber>
      <PageNumber>1105</PageNumber>
    </MainItem>
  </ItemGroup>
  <ItemGroup>
    <MainItem>
      <Key>Walton</Key>
      <Forenames>J. W.</Forenames>
      <PageNumber>531</PageNumber>
    </MainItem>
  </ItemGroup>
  <ItemGroup>
    <MainItem>
      <Key>Ward</Key>
      <Forenames>A. B</Forenames>
      <PageNumber>93</PageNumber>
    </MainItem>
  </ItemGroup>
  <ItemGroup>
    <MainItem>
      <Key>Watson</Key>
      <Forenames>J. D.</Forenames>
      <PageNumber>928</PageNumber>
    </MainItem>
  </ItemGroup>
  <KeyDitto>___ ___ ___</KeyDitto>
  <ItemGroup>
    <MainItem>
      <Key>Watson-Smyth</Key>
      <Forenames>C. E</Forenames>
      <PageNumber>1711</PageNumber>
    </MainItem>
  </ItemGroup>
  <ItemGroup>
    <MainItem>
      <Key>Webb</Key>
      <Forenames>R. M</Forenames>
      <PageNumber>1105</PageNumber>
    </MainItem>
  </ItemGroup>
  <ItemGroup>
    <MainItem>
      <Key>Weguelin</Key>
      <Forenames>J.</Forenames>
      <PageNumber>1712</PageNumber>
    </MainItem>
  </ItemGroup>
  <ItemGroup>
    <MainItem>
      <Key>Wemyss</Key>
      <Forenames>W. M.</Forenames>
      <PageNumber>383</PageNumber>
    </MainItem>
  </ItemGroup>
  <ItemGroup>
    <MainItem>
      <Key>Western</Key>
      <Forenames>B. J. M</Forenames>
      <PageNumber>93</PageNumber>
    </MainItem>
  </ItemGroup>
  <ItemGroup>
    <MainItem>
      <Key>Weston</Key>
      <Forenames>L. A.</Forenames>
      <PageNumber>1396</PageNumber>
    </MainItem>
  </ItemGroup>
  <ItemGroup>
    <MainItem>
      <Key>Wheatley</Key>
      <Forenames>W. G.</Forenames>
      <Text>... '</Text>
      <PageNumber>661</PageNumber>
    </MainItem>
  </ItemGroup>
  <ItemGroup>
    <MainItem>
      <Key>White</Key>
      <Forenames>S. J</Forenames>
      <PageNumber>790</PageNumber>
    </MainItem>
  </ItemGroup>
  <ItemGroup>
    <MainItem>
      <Key>Whitehead</Key>
      <Forenames>J</Forenames>
      <PageNumber>790</PageNumber>
    </MainItem>
  </ItemGroup>
  <ItemGroup>
    <MainItem>
      <Key>Whyte</Key>
      <Forenames>R</Forenames>
      <PageNumber>661</PageNumber>
    </MainItem>
  </ItemGroup>
  <ItemGroup>
    <MainItem>
      <Key>Wilcox</Key>
      <Forenames>S. W</Forenames>
      <PageNumber>928</PageNumber>
    </MainItem>
  </ItemGroup>
  <ItemGroup>
    <MainItem>
      <Key>Willcox</Key>
      <Forenames>E. W</Forenames>
      <PageNumber>1105</PageNumber>
    </MainItem>
  </ItemGroup>
  <ItemGroup>
    <MainItem>
      <Key>Williams</Key>
      <Forenames>C. F</Forenames>
      <PageNumber>227</PageNumber>
      <PageNumber>1105</PageNumber>
    </MainItem>
  </ItemGroup>
  <KeyDitto>___ ___ ___</KeyDitto>
  <ItemGroup>
    <MainItem>
      <Key>
        <KeyDitto>___ ___ ___</KeyDitto>
      </Key>
      <Forenames>S</Forenames>
      <Text>A</Text>
      <PageNumber>93</PageNumber>
    </MainItem>
  </ItemGroup>
  <ItemGroup>
    <MainItem>
      <Key>Witheford</Key>
      <Forenames>H. E</Forenames>
      <PageNumber>928</PageNumber>
    </MainItem>
  </ItemGroup>
  <ItemGroup>
    <MainItem>
      <Key>Wood</Key>
      <Forenames>C. D. C. D</Forenames>
      <Text>£</Text>
      <PageNumber>3</PageNumber>
    </MainItem>
  </ItemGroup>
  <ItemGroup>
    <MainItem>
      <Key>Wooldridge</Key>
      <Forenames>J. W. T</Forenames>
      <PageNumber>790</PageNumber>
    </MainItem>
  </ItemGroup>
  <ItemGroup>
    <MainItem>
      <Key>Wootton</Key>
      <Forenames>E. A.</Forenames>
      <PageNumber>1849</PageNumber>
    </MainItem>
  </ItemGroup>
  <ItemGroup>
    <MainItem>
      <Key>Wright</Key>
      <Forenames>C. H. E</Forenames>
      <PageNumber>661</PageNumber>
    </MainItem>
  </ItemGroup>
  <KeyDitto>___ ___</KeyDitto>
  <ItemGroup>
    <MainItem>
      <Key>Wylly</Key>
      <Forenames>G. G. E</Forenames>
      <PageNumber>1543</PageNumber>
    </MainItem>
  </ItemGroup>
  <ItemGroup>
    <MainItem>
      <Key>Young</Key>
      <Forenames>S</Forenames>
      <PageNumber>383</PageNumber>
    </MainItem>
  </ItemGroup>
  <SectionTitle>Indian Medical Service and Indian Medical Department</SectionTitle>
  <ItemGroup>
    <MainItem>
      <Key>Aitken</Key>
      <Forenames>J</Forenames>
      <PageNumber>928</PageNumber>
    </MainItem>
  </ItemGroup>
  <ItemGroup>
    <MainItem>
      <Key>Askari</Key>
      <Forenames>S. W. H</Forenames>
      <PageNumber>928</PageNumber>
    </MainItem>
  </ItemGroup>
  <ItemGroup>
    <MainItem>
      <Key>Bhargava</Key>
      <Forenames>D. P</Forenames>
      <PageNumber>227</PageNumber>
    </MainItem>
  </ItemGroup>
  <ItemGroup>
    <MainItem>
      <Key>Bharucha</Key>
      <Forenames>P. B. I</Forenames>
      <Text>7 Bradfield, E. W. C</Text>
      <PageNumber>227</PageNumber>
    </MainItem>
  </ItemGroup>
  <ItemGroup>
    <MainItem>
      <Key>Brandenbourg</Key>
      <Forenames>L. F.</Forenames>
      <PageNumber>94</PageNumber>
    </MainItem>
  </ItemGroup>
  <ItemGroup>
    <MainItem>
      <Key>Brown</Key>
      <Forenames>A. S</Forenames>
      <PageNumber>928</PageNumber>
    </MainItem>
  </ItemGroup>
  <ItemGroup>
    <MainItem>
      <Key>Candy</Key>
      <Forenames>R. H</Forenames>
      <PageNumber>1712</PageNumber>
    </MainItem>
  </ItemGroup>
  <ItemGroup>
    <MainItem>
      <Key>Cotton</Key>
      <Forenames>E. A</Forenames>
      <PageNumber>1105</PageNumber>
    </MainItem>
  </ItemGroup>
  <ItemGroup>
    <MainItem>
      <Key>Craig</Key>
      <Forenames>A. H</Forenames>
      <PageNumber>661</PageNumber>
    </MainItem>
  </ItemGroup>
  <ItemGroup>
    <MainItem>
      <Key>Dockery</Key>
      <Forenames>G</Forenames>
      <Text>J-</Text>
      <PageNumber>543</PageNumber>
    </MainItem>
  </ItemGroup>
  <ItemGroup>
    <MainItem>
      <Key>Doyle</Key>
      <Forenames>G. W</Forenames>
      <PageNumber>1712</PageNumber>
    </MainItem>
  </ItemGroup>
  <ItemGroup>
    <MainItem>
      <Key>Fraser</Key>
      <Forenames>K. D</Forenames>
      <PageNumber>928</PageNumber>
    </MainItem>
  </ItemGroup>
  <ItemGroup>
    <MainItem>
      <Key>Gade</Key>
      <Forenames>O. H</Forenames>
      <PageNumber>94</PageNumber>
    </MainItem>
  </ItemGroup>
  <ItemGroup>
    <MainItem>
      <Key>Graham</Key>
      <Forenames>G. K</Forenames>
      <PageNumber>1396</PageNumber>
    </MainItem>
  </ItemGroup>
  <ItemGroup>
    <MainItem>
      <Key>Griggs</Key>
      <Forenames>W. D. P</Forenames>
      <PageNumber>93</PageNumber>
    </MainItem>
  </ItemGroup>
  <ItemGroup>
    <MainItem>
      <Key>Guild</Key>
      <Forenames>A. B</Forenames>
      <PageNumber>1712</PageNumber>
    </MainItem>
  </ItemGroup>
  <ItemGroup>
    <MainItem>
      <Key>Haji</Key>
      <Forenames>H. S. G</Forenames>
      <PageNumber>661</PageNumber>
    </MainItem>
  </ItemGroup>
  <ItemGroup>
    <MainItem>
      <Key>Harrison</Key>
      <Forenames>D. H.</Forenames>
      <PageNumber>928</PageNumber>
    </MainItem>
  </ItemGroup>
  <ItemGroup>
    <MainItem>
      <Key>Haughton</Key>
      <Forenames>S. G. S</Forenames>
      <PageNumber>928</PageNumber>
    </MainItem>
  </ItemGroup>
  <ItemGroup>
    <MainItem>
      <Key>Hayes</Key>
      <Forenames>G. T. M</Forenames>
      <PageNumber>928</PageNumber>
    </MainItem>
  </ItemGroup>
  <ItemGroup>
    <MainItem>
      <Key>Houghton</Key>
      <Forenames>S. G. S.</Forenames>
      <PageNumber>661</PageNumber>
    </MainItem>
  </ItemGroup>
  <ItemGroup>
    <MainItem>
      <Key>Jolly</Key>
      <Forenames>G. G</Forenames>
      <PageNumber>928</PageNumber>
      <PageNumber>1246</PageNumber>
    </MainItem>
  </ItemGroup>
  <ItemGroup>
    <MainItem>
      <Key>Kent</Key>
      <Forenames>P.</Forenames>
      <PageNumber>928</PageNumber>
    </MainItem>
  </ItemGroup>
  <ItemGroup>
    <MainItem>
      <Key>Kingston</Key>
      <Forenames>A. E.</Forenames>
      <PageNumber>1396</PageNumber>
    </MainItem>
  </ItemGroup>
  <ItemGroup>
    <MainItem>
      <Key>Kureishi</Key>
      <Forenames>M. D. A.</Forenames>
      <PageNumber>661</PageNumber>
    </MainItem>
  </ItemGroup>
  <ItemGroup>
    <MainItem>
      <Key>McCutcheon</Key>
      <Forenames>W. M.</Forenames>
      <PageNumber>93</PageNumber>
    </MainItem>
  </ItemGroup>
  <ItemGroup>
    <MainItem>
      <Key>Mathews</Key>
      <Forenames>A. E.</Forenames>
      <PageNumber>1712</PageNumber>
    </MainItem>
  </ItemGroup>
  <ItemGroup>
    <MainItem>
      <Key>Michelson</Key>
      <Forenames>G. S.</Forenames>
      <PageNumber>928</PageNumber>
    </MainItem>
  </ItemGroup>
  <ItemGroup>
    <MainItem>
      <Key>Moody</Key>
      <Forenames>W. J .</Forenames>
      <PageNumber>93</PageNumber>
    </MainItem>
  </ItemGroup>
  <ItemGroup>
    <MainItem>
      <Key>Nardell</Key>
      <Forenames>S. G .</Forenames>
      <PageNumber>928</PageNumber>
    </MainItem>
  </ItemGroup>
  <ItemGroup>
    <MainItem>
      <Key>O</Key>
      <Text>'Connor, W. W</Text>
      <PageNumber>1105</PageNumber>
    </MainItem>
  </ItemGroup>
  <ItemGroup>
    <MainItem>
      <Key>O</Key>
      <Text>'Riordan, J. P</Text>
      <PageNumber>928</PageNumber>
    </MainItem>
  </ItemGroup>
  <ItemGroup>
    <MainItem>
      <Key>Paton</Key>
      <Forenames>W. C .</Forenames>
      <PageNumber>1712</PageNumber>
    </MainItem>
  </ItemGroup>
  <ItemGroup>
    <MainItem>
      <Key>Peten</Key>
      <Forenames>C. W. E.</Forenames>
      <PageNumber>1712</PageNumber>
    </MainItem>
  </ItemGroup>
  <ItemGroup>
    <MainItem>
      <Key>Rees</Key>
      <Forenames>H .</Forenames>
      <PageNumber>1105</PageNumber>
    </MainItem>
  </ItemGroup>
  <ItemGroup>
    <MainItem>
      <Key>Rodgers</Key>
      <Forenames>M. C. R.</Forenames>
      <PageNumber>928</PageNumber>
      <PageNumber>1849</PageNumber>
    </MainItem>
  </ItemGroup>
  <ItemGroup>
    <MainItem>
      <Key>Sein</Key>
      <Forenames>H. M .</Forenames>
      <PageNumber>1105</PageNumber>
    </MainItem>
  </ItemGroup>
  <ItemGroup>
    <MainItem>
      <Key>Thomas</Key>
      <Forenames>T. H.</Forenames>
      <PageNumber>1712</PageNumber>
    </MainItem>
  </ItemGroup>
  <ItemGroup>
    <MainItem>
      <Key>Traynor</Key>
      <Forenames>T. W.</Forenames>
      <PageNumber>1712</PageNumber>
    </MainItem>
  </ItemGroup>
  <ItemGroup>
    <MainItem>
      <Key>West</Key>
      <Forenames>A. W .</Forenames>
      <PageNumber>1396</PageNumber>
    </MainItem>
  </ItemGroup>
  <ItemGroup>
    <MainItem>
      <Key>Williams</Key>
      <Forenames>W. E. R.</Forenames>
      <PageNumber>1105</PageNumber>
    </MainItem>
  </ItemGroup>
  <ItemGroup>
    <MainItem>
      <Key>Williamson</Key>
      <Forenames>H.</Forenames>
      <PageNumber>94</PageNumber>
    </MainItem>
  </ItemGroup>
  <ItemGroup>
    <MainItem>
      <Key>Wilson</Key>
      <Forenames>D. S.</Forenames>
      <PageNumber>93</PageNumber>
    </MainItem>
  </ItemGroup>
  <ItemGroup>
    <MainItem>
      <Key>Wormald</Key>
      <Forenames>P. J.</Forenames>
      <PageNumber>928</PageNumber>
    </MainItem>
  </ItemGroup>
  <ItemGroup>
    <MainItem>
      <Key>Yerbury</Key>
      <Forenames>R. O</Forenames>
      <PageNumber>928</PageNumber>
    </MainItem>
  </ItemGroup>
  <SectionTitle>Royal Indian Navy</SectionTitle>
  <ItemGroup>
    <MainItem>
      <Key>Bergner</Key>
      <Forenames>C. R. L.</Forenames>
      <PageNumber>1395</PageNumber>
    </MainItem>
  </ItemGroup>
  <ItemGroup>
    <MainItem>
      <Key>Cameron</Key>
      <Forenames>J.</Forenames>
      <PageNumber>93</PageNumber>
    </MainItem>
  </ItemGroup>
  <ItemGroup>
    <MainItem>
      <Key>Charanjit</Key>
      <Forenames>Lai Bhandari</Forenames>
      <PageNumber>1711</PageNumber>
    </MainItem>
  </ItemGroup>
  <ItemGroup>
    <MainItem>
      <Key>Ellison</Key>
      <Forenames>I. A. G.</Forenames>
      <PageNumber>928</PageNumber>
    </MainItem>
  </ItemGroup>
  <ItemGroup>
    <MainItem>
      <Key>Legood</Key>
      <Forenames>J. R.</Forenames>
      <PageNumber>928</PageNumber>
    </MainItem>
  </ItemGroup>
  <ItemGroup>
    <MainItem>
      <Key>McClement</Key>
      <Forenames>R. G. G.</Forenames>
      <PageNumber>93</PageNumber>
    </MainItem>
  </ItemGroup>
  <ItemGroup>
    <MainItem>
      <Key>Taylor</Key>
      <Forenames>G.</Forenames>
      <PageNumber>1711</PageNumber>
    </MainItem>
  </ItemGroup>
  <ItemGroup>
    <MainItem>
      <Key>Triloki</Key>
      <Forenames>Nath Kochhar</Forenames>
      <PageNumber>1711</PageNumber>
    </MainItem>
  </ItemGroup>
  <SectionTitle>Commands and Staff</SectionTitle>
  <ItemGroup>
    <MainItem>
      <Key>O</Key>
      <Text>'Brien, B. P. T</Text>
      <PageNumber>928</PageNumber>
    </MainItem>
  </ItemGroup>
  <SectionTitle>Burman Army</SectionTitle>
  <ItemGroup>
    <MainItem>
      <Key>Beaman</Key>
      <Forenames>G. G. W. H</Forenames>
      <PageNumber>384</PageNumber>
    </MainItem>
  </ItemGroup>
  <ItemGroup>
    <MainItem>
      <Key>Blake</Key>
      <Forenames>D</Forenames>
      <PageNumber>383</PageNumber>
    </MainItem>
  </ItemGroup>
  <ItemGroup>
    <MainItem>
      <Key>Bodeker</Key>
      <Forenames>W. B. T</Forenames>
      <PageNumber>383</PageNumber>
    </MainItem>
  </ItemGroup>
  <ItemGroup>
    <MainItem>
      <Key>Booker</Key>
      <Forenames>E. W</Forenames>
      <PageNumber>384</PageNumber>
    </MainItem>
  </ItemGroup>
  <ItemGroup>
    <MainItem>
      <Key>Buchanan</Key>
      <Forenames>P. C</Forenames>
      <PageNumber>384</PageNumber>
    </MainItem>
  </ItemGroup>
  <ItemGroup>
    <MainItem>
      <Key>Carne</Key>
      <Forenames>G. P</Forenames>
      <PageNumber>384</PageNumber>
    </MainItem>
  </ItemGroup>
  <ItemGroup>
    <MainItem>
      <Key>Carrington</Key>
      <Forenames>F. C.</Forenames>
      <PageNumber>1712</PageNumber>
    </MainItem>
  </ItemGroup>
  <ItemGroup>
    <MainItem>
      <Key>Castens</Key>
      <Forenames>H. E</Forenames>
      <PageNumber>384</PageNumber>
    </MainItem>
  </ItemGroup>
  <ItemGroup>
    <MainItem>
      <Key>Chesterton</Key>
      <Forenames>P. H</Forenames>
      <PageNumber>383</PageNumber>
    </MainItem>
  </ItemGroup>
  <ItemGroup>
    <MainItem>
      <Key>Cozens</Key>
      <Forenames>D. H</Forenames>
      <PageNumber>384</PageNumber>
    </MainItem>
  </ItemGroup>
  <ItemGroup>
    <MainItem>
      <Key>Curry</Key>
      <Forenames>A. R</Forenames>
      <PageNumber>384</PageNumber>
    </MainItem>
  </ItemGroup>
  <ItemGroup>
    <MainItem>
      <Key>Dix</Key>
      <Forenames>C. B.</Forenames>
      <PageNumber>384</PageNumber>
    </MainItem>
  </ItemGroup>
  <ItemGroup>
    <MainItem>
      <Key>Eccles</Key>
      <Forenames>G. M .</Forenames>
      <PageNumber>384</PageNumber>
    </MainItem>
  </ItemGroup>
  <ItemGroup>
    <MainItem>
      <Key>Edgley</Key>
      <Forenames>J. A. E .</Forenames>
      <PageNumber>384</PageNumber>
    </MainItem>
  </ItemGroup>
  <ItemGroup>
    <MainItem>
      <Key>Ferrier</Key>
      <Forenames>A. J .</Forenames>
      <PageNumber>383</PageNumber>
    </MainItem>
  </ItemGroup>
  <ItemGroup>
    <MainItem>
      <Key>Forbes</Key>
      <Forenames>E. G.</Forenames>
      <PageNumber>384</PageNumber>
    </MainItem>
  </ItemGroup>
  <ItemGroup>
    <MainItem>
      <Key>Freshney</Key>
      <Forenames>M. A.</Forenames>
      <PageNumber>384</PageNumber>
    </MainItem>
  </ItemGroup>
  <ItemGroup>
    <MainItem>
      <Key>Garthwaite</Key>
      <Forenames>P. F.</Forenames>
      <PageNumber>384</PageNumber>
    </MainItem>
  </ItemGroup>
  <ItemGroup>
    <MainItem>
      <Key>Gaudie</Key>
      <Forenames>L. G.</Forenames>
      <PageNumber>384</PageNumber>
    </MainItem>
  </ItemGroup>
  <ItemGroup>
    <MainItem>
      <Key>Gauld</Key>
      <Forenames>J.</Forenames>
      <PageNumber>1712</PageNumber>
    </MainItem>
  </ItemGroup>
  <ItemGroup>
    <MainItem>
      <Key>Griffin</Key>
      <Forenames>S. R .</Forenames>
      <PageNumber>384</PageNumber>
    </MainItem>
  </ItemGroup>
  <ItemGroup>
    <MainItem>
      <Key>Griffiths</Key>
      <Forenames>W. D .</Forenames>
      <PageNumber>384</PageNumber>
    </MainItem>
  </ItemGroup>
  <ItemGroup>
    <MainItem>
      <Key>Gunn</Key>
      <Forenames>M. S. T .</Forenames>
      <PageNumber>1713</PageNumber>
    </MainItem>
  </ItemGroup>
  <ItemGroup>
    <MainItem>
      <Key>Hartnoll</Key>
      <Forenames>E. S.</Forenames>
      <PageNumber>383</PageNumber>
    </MainItem>
  </ItemGroup>
  <ItemGroup>
    <MainItem>
      <Key>Hearsey</Key>
      <Forenames>R.</Forenames>
      <PageNumber>383</PageNumber>
    </MainItem>
  </ItemGroup>
  <ItemGroup>
    <MainItem>
      <Key>Hedley</Key>
      <Forenames>J. D. H.</Forenames>
      <PageNumber>384</PageNumber>
    </MainItem>
  </ItemGroup>
  <ItemGroup>
    <MainItem>
      <Key>Hogg</Key>
      <Forenames>N. J. N. T.</Forenames>
      <PageNumber>384</PageNumber>
    </MainItem>
  </ItemGroup>
  <ItemGroup>
    <MainItem>
      <Key>Hughes</Key>
      <Text>C. E</Text>
      <PageNumber>1712</PageNumber>
    </MainItem>
  </ItemGroup>
  <ItemGroup>
    <MainItem>
      <Key>Jones</Key>
      <Text>LI</Text>
      <PageNumber>1712</PageNumber>
    </MainItem>
  </ItemGroup>
  <ItemGroup>
    <MainItem>
      <Key>Kirby</Key>
      <Forenames>H. L .</Forenames>
      <PageNumber>383</PageNumber>
    </MainItem>
  </ItemGroup>
  <ItemGroup>
    <MainItem>
      <Key>Leach</Key>
      <Forenames>E. R.</Forenames>
      <PageNumber>384</PageNumber>
    </MainItem>
  </ItemGroup>
  <ItemGroup>
    <MainItem>
      <Key>Lewis</Key>
      <Forenames>D. R.</Forenames>
      <Text>-</Text>
      <PageNumber>383</PageNumber>
    </MainItem>
  </ItemGroup>
  <ItemGroup>
    <MainItem>
      <Key>Lutter</Key>
      <Forenames>D. P. Ff</Forenames>
      <PageNumber>384</PageNumber>
    </MainItem>
  </ItemGroup>
  <ItemGroup>
    <MainItem>
      <Key>McColl</Key>
      <Forenames>H. H .</Forenames>
      <PageNumber>383</PageNumber>
    </MainItem>
  </ItemGroup>
  <ItemGroup>
    <MainItem>
      <Key>McDowall</Key>
      <Forenames>C. A.</Forenames>
      <PageNumber>384</PageNumber>
    </MainItem>
  </ItemGroup>
  <ItemGroup>
    <MainItem>
      <Key>Maclachlan</Key>
      <Forenames>W. P. G.</Forenames>
      <PageNumber>384</PageNumber>
    </MainItem>
  </ItemGroup>
  <ItemGroup>
    <MainItem>
      <Key>Mahomed</Key>
      <Forenames>Nural Ameen</Forenames>
      <Text>-</Text>
      <PageNumber>383</PageNumber>
    </MainItem>
  </ItemGroup>
  <ItemGroup>
    <MainItem>
      <Key>Maung</Key>
      <Title>Aye .</Title>
      <PageNumber>384</PageNumber>
    </MainItem>
  </ItemGroup>
  <ItemGroup>
    <MainItem>
      <Key>Maung</Key>
      <Forenames>Myint Thein</Forenames>
      <PageNumber>384</PageNumber>
    </MainItem>
  </ItemGroup>
  <ItemGroup>
    <MainItem>
      <Key>Meggitt</Key>
      <Forenames>F. J.</Forenames>
      <PageNumber>383</PageNumber>
    </MainItem>
  </ItemGroup>
  <ItemGroup>
    <MainItem>
      <Key>Nalty</Key>
      <Forenames>H. V .</Forenames>
      <PageNumber>1712</PageNumber>
    </MainItem>
  </ItemGroup>
  <ItemGroup>
    <MainItem>
      <Key>Oats</Key>
      <Forenames>J. F .</Forenames>
      <PageNumber>384</PageNumber>
    </MainItem>
  </ItemGroup>
  <ItemGroup>
    <MainItem>
      <Key>Peacock</Key>
      <Forenames>D. H .</Forenames>
      <PageNumber>384</PageNumber>
    </MainItem>
  </ItemGroup>
  <ItemGroup>
    <MainItem>
      <Key>Penfold</Key>
      <Forenames>S. R .</Forenames>
      <PageNumber>383</PageNumber>
    </MainItem>
  </ItemGroup>
  <ItemGroup>
    <MainItem>
      <Key>Pryke</Key>
      <Forenames>P. S .</Forenames>
      <PageNumber>384</PageNumber>
    </MainItem>
  </ItemGroup>
  <ItemGroup>
    <MainItem>
      <Key>Reading</Key>
      <Forenames>C. C. T.</Forenames>
      <PageNumber>383</PageNumber>
    </MainItem>
  </ItemGroup>
  <ItemGroup>
    <MainItem>
      <Key>Reynolds</Key>
      <Forenames>F. H.</Forenames>
      <PageNumber>383</PageNumber>
    </MainItem>
  </ItemGroup>
  <ItemGroup>
    <MainItem>
      <Key>Richmond</Key>
      <Forenames>G. N.</Forenames>
      <PageNumber>383</PageNumber>
    </MainItem>
  </ItemGroup>
  <ItemGroup>
    <MainItem>
      <Key>Robertson</Key>
      <Forenames>H. F.</Forenames>
      <PageNumber>383</PageNumber>
    </MainItem>
  </ItemGroup>
  <ItemGroup>
    <MainItem>
      <Key>Sayres</Key>
      <Forenames>R. J.</Forenames>
      <PageNumber>383</PageNumber>
    </MainItem>
  </ItemGroup>
  <ItemGroup>
    <MainItem>
      <Key>Scott</Key>
      <Forenames>I. C. G .</Forenames>
      <PageNumber>384</PageNumber>
    </MainItem>
  </ItemGroup>
  <ItemGroup>
    <MainItem>
      <Key>Shelley</Key>
      <Forenames>J. G .</Forenames>
      <PageNumber>384</PageNumber>
    </MainItem>
  </ItemGroup>
  <ItemGroup>
    <MainItem>
      <Key>Simmons</Key>
      <Forenames>E. C.</Forenames>
      <PageNumber>383</PageNumber>
    </MainItem>
  </ItemGroup>
  <ItemGroup>
    <MainItem>
      <Key>Slade</Key>
      <Forenames>J. W. C</Forenames>
      <Text>-</Text>
      <PageNumber>383</PageNumber>
    </MainItem>
  </ItemGroup>
  <ItemGroup>
    <MainItem>
      <Key>Smith</Key>
      <Forenames>W. S .</Forenames>
      <PageNumber>384</PageNumber>
    </MainItem>
  </ItemGroup>
  <ItemGroup>
    <MainItem>
      <Key>Smitz</Key>
      <Forenames>W. B .</Forenames>
      <PageNumber>383</PageNumber>
    </MainItem>
  </ItemGroup>
  <ItemGroup>
    <MainItem>
      <Key>Sutherland</Key>
      <Forenames>C.</Forenames>
      <PageNumber>383</PageNumber>
    </MainItem>
  </ItemGroup>
  <ItemGroup>
    <MainItem>
      <Key>
        <KeyDitto>___ ___ ___</KeyDitto>
      </Key>
      <Forenames>J. W. R</Forenames>
      <Text>-</Text>
      <PageNumber>383</PageNumber>
    </MainItem>
  </ItemGroup>
  <ItemGroup>
    <MainItem>
      <Key>Ure</Key>
      <Forenames>J. G .</Forenames>
      <PageNumber>384</PageNumber>
    </MainItem>
  </ItemGroup>
  <ItemGroup>
    <MainItem>
      <Key>Vernall</Key>
      <Forenames>L. J .</Forenames>
      <PageNumber>384</PageNumber>
    </MainItem>
  </ItemGroup>
  <ItemGroup>
    <MainItem>
      <Key>Vorley</Key>
      <Forenames>J. S .</Forenames>
      <PageNumber>383</PageNumber>
    </MainItem>
  </ItemGroup>
  <ItemGroup>
    <MainItem>
      <Key>Watson</Key>
      <Forenames>N. G .</Forenames>
      <PageNumber>384</PageNumber>
    </MainItem>
  </ItemGroup>
  <ItemGroup>
    <MainItem>
      <Key>
        <KeyDitto>___ ___ ___</KeyDitto>
      </Key>
      <Forenames>R .</Forenames>
      <PageNumber>383</PageNumber>
    </MainItem>
  </ItemGroup>
  <ItemGroup>
    <MainItem>
      <Key>Wemyss</Key>
      <Forenames>W. M.</Forenames>
      <PageNumber>383</PageNumber>
    </MainItem>
  </ItemGroup>
  <ItemGroup>
    <MainItem>
      <Key>Whitrow</Key>
      <Forenames>E. H.</Forenames>
      <PageNumber>384</PageNumber>
    </MainItem>
  </ItemGroup>
  <ItemGroup>
    <MainItem>
      <Key>Wood</Key>
      <Forenames>R. W.</Forenames>
      <PageNumber>284</PageNumber>
    </MainItem>
  </ItemGroup>
  <ItemGroup>
    <MainItem>
      <Key>Young</Key>
      <Forenames>S .</Forenames>
      <PageNumber>383</PageNumber>
    </MainItem>
  </ItemGroup>
  <CategoryTitle>NAVAL PROMOTIONS</CategoryTitle>
  <SectionTitle>Aide-de-Camp to His Majesty the King</SectionTitle>
  <ItemGroup>
    <MainItem>
      <Key>Bennett</Key>
      <Forenames>D. C</Forenames>
      <PageNumber>22</PageNumber>
    </MainItem>
  </ItemGroup>
  <SubSectionTitle>Admirals of the Fleet</SubSectionTitle>
  <ItemGroup>
    <MainItem>
      <Key>Brock</Key>
      <Title>Sir</Title>
      <Forenames>O.</Forenames>
      <Text>de B</Text>
      <PageNumber>1394</PageNumber>
    </MainItem>
  </ItemGroup>
  <ItemGroup>
    <MainItem>
      <Key>Field</Key>
      <Title>Sir</Title>
      <Forenames>F. L.</Forenames>
      <PageNumber>1394</PageNumber>
    </MainItem>
  </ItemGroup>
  <ItemGroup>
    <MainItem>
      <Key>Keyes</Key>
      <Text>SirR. J. B., Bt</Text>
      <PageNumber>1394</PageNumber>
    </MainItem>
  </ItemGroup>
  <ItemGroup>
    <MainItem>
      <Key>Oliver</Key>
      <Title>Sir</Title>
      <Forenames>H. F.</Forenames>
      <PageNumber>1394</PageNumber>
    </MainItem>
  </ItemGroup>
  <ItemGroup>
    <MainItem>
      <Key>Tyrwhitt</Key>
      <Title>Sir</Title>
      <Forenames>R. Y.</Forenames>
      <Text>, Bt</Text>
      <PageNumber>1394</PageNumber>
    </MainItem>
  </ItemGroup>
  <SubSectionTitle>Captains</SubSectionTitle>
  <ItemGroup>
    <MainItem>
      <Key>Bateson</Key>
      <Forenames>S. L.</Forenames>
      <PageNumber>20</PageNumber>
    </MainItem>
  </ItemGroup>
  <ItemGroup>
    <MainItem>
      <Key>Bethell</Key>
      <Forenames>J. S.</Forenames>
      <PageNumber>20</PageNumber>
    </MainItem>
  </ItemGroup>
  <ItemGroup>
    <MainItem>
      <Key>Bickford</Key>
      <Forenames>J. G .</Forenames>
      <PageNumber>20</PageNumber>
    </MainItem>
  </ItemGroup>
  <ItemGroup>
    <MainItem>
      <Key>Dickson</Key>
      <Forenames>R. K.</Forenames>
      <PageNumber>20</PageNumber>
    </MainItem>
  </ItemGroup>
  <ItemGroup>
    <MainItem>
      <Key>Eccles</Key>
      <Forenames>J. A. S .</Forenames>
      <PageNumber>20</PageNumber>
    </MainItem>
  </ItemGroup>
  <ItemGroup>
    <MainItem>
      <Key>Eveleigh</Key>
      <Forenames>M. H.</Forenames>
      <PageNumber>20</PageNumber>
    </MainItem>
  </ItemGroup>
  <ItemGroup>
    <MainItem>
      <Key>Farquhar</Key>
      <Forenames>J. W.</Forenames>
      <PageNumber>20</PageNumber>
    </MainItem>
  </ItemGroup>
  <ItemGroup>
    <MainItem>
      <Key>Friedberger</Key>
      <Forenames>W. H. D.</Forenames>
      <PageNumber>20</PageNumber>
    </MainItem>
  </ItemGroup>
  <ItemGroup>
    <MainItem>
      <Key>Gilmour</Key>
      <Forenames>D</Forenames>
      <PageNumber>20</PageNumber>
    </MainItem>
  </ItemGroup>
  <ItemGroup>
    <MainItem>
      <Key>Hughes-Hallett</Key>
      <Forenames>C. C</Forenames>
      <PageNumber>20</PageNumber>
    </MainItem>
  </ItemGroup>
  <ItemGroup>
    <MainItem>
      <Key>Josselyn</Key>
      <Forenames>J. W</Forenames>
      <PageNumber>20</PageNumber>
    </MainItem>
  </ItemGroup>
  <ItemGroup>
    <MainItem>
      <Key>Lees</Key>
      <Forenames>D. M</Forenames>
      <PageNumber>20</PageNumber>
    </MainItem>
  </ItemGroup>
  <ItemGroup>
    <MainItem>
      <Key>McLaughlin</Key>
      <Forenames>P. V</Forenames>
      <PageNumber>20</PageNumber>
    </MainItem>
  </ItemGroup>
  <ItemGroup>
    <MainItem>
      <Key>Murray-Smith</Key>
      <Forenames>H. S</Forenames>
      <PageNumber>20</PageNumber>
    </MainItem>
  </ItemGroup>
  <ItemGroup>
    <MainItem>
      <Key>Parham</Key>
      <Forenames>F. R .</Forenames>
      <PageNumber>20</PageNumber>
    </MainItem>
  </ItemGroup>
  <ItemGroup>
    <MainItem>
      <Key>Pleydell-Bouverie</Key>
      <Title>Hon.</Title>
      <Forenames>E.</Forenames>
      <PageNumber>20</PageNumber>
    </MainItem>
  </ItemGroup>
  <KeyDitto>___ ___ ___ ___ ___ ___ ___</KeyDitto>
</Index>

